dep_redis/__init__.py
pyproject.toml
tests/__init__.py
tests/test_module.py
dep_plugin_redis-0.1.0.dist-info/WHEEL
dep_plugin_redis-0.1.0.dist-info/METADATA
dep_plugin_redis-0.1.0.dist-info/RECORD
