Metadata-Version: 2.1
Name: dep-plugin-redis
Version: 0.1.0
Summary: 
Author: everhide
Author-email: i.tolkachnikov@gmail.com
Requires-Python: >=3.9,<4.0
Classifier: Programming Language :: Python :: 3
Classifier: Programming Language :: Python :: 3.10
Classifier: Programming Language :: Python :: 3.9
Requires-Dist: aioredis[hiredis] (>=2.0.1,<3.0.0)
Requires-Dist: dep-spec (>=0.5.6,<0.6.0)
